<annotation>
	<folder>5tl</folder>
	<filename>IMG_20180728_203906.jpg</filename>
	<path>C:\Users\trabz\Desktop\ownDatafrcnn\data\5tl\IMG_20180728_203906.jpg</path>
	<source>
		<database>Unknown</database>
	</source>
	<size>
		<width>480</width>
		<height>640</height>
		<depth>3</depth>
	</size>
	<segmented>0</segmented>
	<object>
		<name>bes</name>
		<pose>Unspecified</pose>
		<truncated>1</truncated>
		<difficult>0</difficult>
		<bndbox>
			<xmin>1</xmin>
			<ymin>100</ymin>
			<xmax>471</xmax>
			<ymax>538</ymax>
		</bndbox>
	</object>
</annotation>
